propinfer/__init__.py
propinfer/deepsets.py
propinfer/experiment.py
propinfer/generator.py
propinfer/model.py
propinfer/model_utils.py
propinfer-1.3.0.dist-info/LICENSE.md
propinfer-1.3.0.dist-info/METADATA
propinfer-1.3.0.dist-info/WHEEL
propinfer-1.3.0.dist-info/top_level.txt
propinfer-1.3.0.dist-info/RECORD
