Metadata-Version: 2.1
Name: propinfer
Version: 1.3.0
Summary: Modular framework to run Property Inference Attacks on Machine Learning models.
Home-page: https://epfl-dlab.github.io/property-inference-attacks/
Author: Léo Meynent
Author-email: leo.meynent@epfl.ch
License: MIT
Project-URL: Repository, https://github.com/epfl-dlab/property-inference-attacks/
Project-URL: Tracker, https://github.com/epfl-dlab/property-inference-attacks/issues
Classifier: Programming Language :: Python :: 3
Classifier: License :: OSI Approved :: MIT License
Classifier: Operating System :: OS Independent
Classifier: Intended Audience :: Science/Research
Requires-Python: >=3.6
License-File: LICENSE.md
Requires-Dist: scikit-learn
Requires-Dist: pandas
Requires-Dist: numpy
Requires-Dist: hydra-core
